[{
  "id": "1574083",
  "username": "teenvogue",
  "full_name": "Teen Vogue",
  "profile_picture": "https://instagram.fbed1-1.fna.fbcdn.net/t51.2885-19/10518223_1649292711961544_1142398452_a.jpg",
  "bio": "Fashion starts here. likeshop.me/teenvogue",
  "website": "http://teenvogue.com",
  "counts": {
    "media": 6397,
    "follows": 2200000,
    "followed_by": 1103
  }
},
{
  "id": "434533",
  "username": "kyliejenner",
  "full_name": "Kylie Jenner",
  "profile_picture": "http://distillery.s3.amazonaws.com/profiles/profile_1574083_75sq_1245656222061.jpg",
  "bio": "Hey guys it's Kylie",
  "website": "http://kylie.com",
  "counts": {
    "media": 5327,
    "follows": 156,
    "followed_by": 99000000
  }
},
{
  "id": "1533383",
  "username": "colesprouse",
  "full_name": "Cole Sprouse",
  "profile_picture": "http://distillery.s3.amazonaws.com/profiles/profile_1574083_75sq_123462222222229061.jpg",
  "bio": " DM me your credit card info. @camera_duels is my other account.",
  "website": "http://colesprouse.com",
  "counts": {
    "media": 831,
    "follows": 477,
    "followed_by": 9600000
  }
},
{
  "id": "221183",
  "username": "iamcardib",
  "full_name": "Cardi B Official IG",
  "profile_picture": "https://instagram.fbed1-1.fna.fbcdn.net/t51.2885-19/s320x320/15802882_1253180011437330_7329418117904334848_a.jpg",
  "bio": "IAMCARDIB.COM | #GBMV1 | #GBMV2 | #BodakYellow | GOD IS GREAT ",
  "website": "http://cardib.com",
  "counts": {
    "media": 5463,
    "follows": 2904,
    "followed_by": 12600000
  }
},
{
  "id": "1574083",
  "username": "snoopdogg",
  "full_name": "Snoop Dogg",
  "profile_picture": "http://distillery.s3.amazonaws.com/profiles/profile_1574083_75sq_1295469061.jpg",
  "bio": "This is my bio",
  "website": "http://snoopdogg.com",
  "counts": {
    "media": 32221,
    "follows": 19800000,
    "followed_by": 2802
  }
},
{
  "id": "111122283",
  "username": "tiffanyhaddish",
  "full_name": "Tiffany Haddish",
  "profile_picture": "https://instagram.fbed1-1.fna.fbcdn.net/t51.2885-19/11251183_1626234757591533_337405679_a.jpg",
  "bio": "People tell me I am funny and good looking. I am just happy to be me. Pre order my book. bit.ly/TiffanyHaddishBook",
  "website": "http://tiffanyhaddish.com",
  "counts": {
    "media": 1443,
    "follows": 2398,
    "followed_by": 718000
  }
},
{
  "id": "88884083",
  "username": "ddlovato",
  "full_name": "Demi Lovato",
  "profile_picture": "https://instagram.fbed1-1.fna.fbcdn.net/t51.2885-19/s320x320/22710424_1870643009615692_4824434934217179136_n.jpg",
  "bio": " Singer, Songwriter, Actress, Entrepreneur, Philanthropist ",
  "website": "http://demilovato.com",
  "counts": {
    "media": 1876,
    "follows": 62100000,
    "followed_by": 330
  }
},
{
  "id": "1",
  "username": "badgalriri",
  "full_name": "Rihanna",
  "profile_picture": "https://instagram.fbed1-1.fna.fbcdn.net/t51.2885-19/11032926_1049846535031474_260957621_a.jpg",
  "bio": " @FentyBeauty is out now!! ri-hanna.io/fentybeauty",
  "website": "http://fenty.com",
  "counts": {
    "media": 4119,
    "follows": 57800000,
    "followed_by": 1271
  }
},
{
  "id": 700,
  "username": "not_a_celebrity",
  "full_name": "Normal Person",
  "profile_picture": null,
  "bio": "Wish I was famous",
  "website": null,
  "counts": {
    "media": 3,
    "follows": 4000,
    "followed_by": 40
  }
}]